{
"type": "FeatureCollection", 
"crs": { "type": "name", "properties": { "name": "urn:ogc:def:crs:OGC:1.3:CRS84" } },
"features": 
[
{ "type": "Feature", "properties": { "latitude":41.2241, "longitude":-6.1922, "time":1, "id": "route1", "name": "Initial" }, "geometry": { "type": "Point", "coordinates": [-6.1922, 41.2241 ] } },
{ "type": "Feature", "properties": { "latitude":41.1991, "longitude":-6.2368, "time":2, "id": "route1", "name": "Along route" }, "geometry": { "type": "Point", "coordinates": [-6.2368, 41.1991 ] } },
{ "type": "Feature", "properties": { "latitude":41.1883, "longitude":-6.2559, "time":3, "id": "route1", "name": "Along route" }, "geometry": { "type": "Point", "coordinates": [-6.2559, 41.1883 ] } },
{ "type": "Feature", "properties": { "latitude":41.1749, "longitude":-6.2796, "time":4, "id": "route1", "name": "Along route" }, "geometry": { "type": "Point", "coordinates": [-6.2796, 41.1749 ] } },
{ "type": "Feature", "properties": { "latitude":41.1648, "longitude":-6.2974, "time":5, "id": "route1", "name": "Along route" }, "geometry": { "type": "Point", "coordinates": [-6.2974, 41.1648 ] } },
{ "type": "Feature", "properties": { "latitude":41.1524, "longitude":-6.3194, "time":6, "id": "route1", "name": "Actual" }, "geometry": { "type": "Point", "coordinates": [-6.3194, 41.1524 ] } }
]
}